pynetgear_enhanced/__init__.py
pynetgear_enhanced/__main__.py
pynetgear_enhanced/commands.py
pynetgear_enhanced/const.py
pynetgear_enhanced/helpers.py
pynetgear_enhanced-0.2.1.dist-info/LICENSE
pynetgear_enhanced-0.2.1.dist-info/METADATA
pynetgear_enhanced-0.2.1.dist-info/WHEEL
pynetgear_enhanced-0.2.1.dist-info/top_level.txt
pynetgear_enhanced-0.2.1.dist-info/zip-safe
pynetgear_enhanced-0.2.1.dist-info/RECORD
