Metadata-Version: 2.1
Name: pynetgear-enhanced
Version: 0.2.1
Summary: Access Netgear routers using their SOAP API
Home-page: http://github.com/roblandry/pynetgear_enhanced
Author: Rob Landry
Author-email: rob@landry.me
License: MIT
Download-URL: http://github.com/roblandry/pynetgear_enhanced/archive/v0.2.1.tar.gz
Platform: UNKNOWN
Requires-Dist: requests (>=2.0)
